PyAutoMakerHuman/__init__.py
PyAutoMakerHuman/__main__.py
PyAutoMakerHuman/custom_signal.py
PyAutoMakerHuman/face.py
PyAutoMakerHuman/hand.py
PyAutoMakerHuman/image.py
PyAutoMakerHuman/launcher.py
PyAutoMakerHuman/launcher_train_tab.py
PyAutoMakerHuman/main_form.py
PyAutoMakerHuman/pose.py
PyAutoMakerHuman/thread.py
PyAutoMakerHuman/train.py
PyAutoMakerHuman/utils.py
PyAutoMakerHuman/models/deploy.prototxt
PyAutoMakerHuman/models/mask_classifier.tflite
PyAutoMakerHuman/models/openface_nn4.small2.v1.t7
PyAutoMakerHuman/models/res10_300x300_ssd_iter_140000.caffemodel
PyAutoMakerHuman-1.2.1.dist-info/LICENSE
PyAutoMakerHuman-1.2.1.dist-info/METADATA
PyAutoMakerHuman-1.2.1.dist-info/WHEEL
PyAutoMakerHuman-1.2.1.dist-info/top_level.txt
PyAutoMakerHuman-1.2.1.dist-info/RECORD
